feedpush-0.2.0.dist-info/METADATA
feedpush-0.2.0.dist-info/WHEEL
feedpush-0.2.0.dist-info/entry_points.txt
feedpush-0.2.0.dist-info/licenses/LICENSE
feedpush/__init__.py
feedpush/main.py
feedpush-0.2.0.dist-info/RECORD
