Metadata-Version: 2.1
Name: feedpush
Version: 0.2.0
Summary: A simple rss/atom feed parser
Keywords: feedpsuh,rss,feed,notify
Author: p7e4
License: GPLv3
Classifier: Programming Language :: Python :: 3
Classifier: Programming Language :: Python :: 3.12
Classifier: License :: OSI Approved :: GNU General Public License v3 (GPLv3)
Project-URL: Repository, https://github.com/p7e4/feedpush
Project-URL: Issues, https://github.com/p7e4/feedpush/issues
Requires-Python: >=3.12
Requires-Dist: rssfeed>=0.3
Requires-Dist: aiohttp>=3.10
